Workbook

Sheet resultado estimado
A1: PRESUPUESTO ESTADO DE RESULTADO
A2: 2024 mayo
A3: Grupo Pilat, S.A.
B6: 44562 | C6: 44593 | D6: 44621 | E6: 44652 | F6: 44682 | G6: 44713 | H6: 44743 | I6: 44774 | J6: 44805 | K6: Oct-22 | L6: Nov-22 | M6: Dic-22 | N6: COSTOS SEGÚN CANT | O6: PRESUPUESTO SEGÚN CANT ENERO 24 | P6: PROMEDIOS IDEALES DIC
A8: Ingresos | Q8: ACTUAL
A9: 4000 - Ingresos | B9: 27246.28 | C9: 30713.79 | D9: 38889.1 | E9: 34286.15 | F9: 33739.3 | G9: 33369.75 | H9: 33203.71 | I9: 38539.7 | J9: 36930.83 | K9: 45761.68 | L9: 38553.57 | M9: 59145.57 | O9: 50000 | P9: 59000 | Q9: =ventas!G2 -> 10578.4
A10: 4003 - Descuento de jubilados | B10: -1527.1 | C10: -1468.43 | D10: -1692.77 | E10: -1632.95 | F10: -1853.47 | G10: -1958.03 | H10: -1916.18 | I10: -2084.59 | J10: -2131.91 | K10: -2025.79 | L10: -2149.01 | M10: -3011.62 | O10: =U10 -> 3800.1342 | P10: -3011.62 | T10: 45601.61 | U10: =T10/12 -> 3800.1342
A11: Total de Ingresos | B11: =B9+B10 -> 25719.18 | C11: =C9+C10 -> 29245.36 | D11: =D9+D10 -> 37196.33 | E11: =E9+E10 -> 32653.2 | F11: =F9+F10 -> 31885.83 | G11: =G9+G10 -> 31411.72 | H11: =H9+H10 -> 31287.53 | I11: =I9+I10 -> 36455.11 | ... M11: =M9+M10 -> 56133.95 | O11: =O9-O10 -> 46199.866 | P11: =P9+P10 -> 55988.38 | Q11: =Q9-O10 -> 6778.2658
A13: Costo de Venta
A14: 5008 - CARNES Y PUERCO | B14: 2149.55 | C14: 1912.97 | D14: 2763.34 | E14: 2423.23 | F14: 2975.96 | G14: 2898.9 | H14: 2998.34 | I14: 3744.16 | J14: 3631.38 | K14: 5111.8186 | L14: 3642.89 | M14: 4379 | O14: =N15+N16+N17+N18+N21+N22+N23+N24+N25+N26+N27+N29+N30+N31+N32+N33 -> 4565.1796 | P14: 3541.7822
A15: chuleta | N15: =[1]CHULETAS!$C$21 -> 1404.5338
A16: churrasco | N16: =[1]CHURRASCO!$C$21 -> 285.96554
A17: costilla para parrilla | N17: ='[1]COSTILLAS ASADAS'!$C$21 -> 391.36152
A18: filete de res | N18: ='[1]FILETE DE RES '!$C$21 -> 405.24574
A19: rincon
A20: lomo | N20: =[2]LOMO!$C$21 -> 236.51472
A21: lomo | N21: =[2]LOMO!$C$21 -> 236.51472
A22: lengua | N22: =[2]LENGUA!$C$21 -> 184.98887
A23: costilla horno | N23: ='[2]COSTILLA HORNO'!$C$21 -> 390.35299
A24: bistec picado | N24: ='[2]BISTEC PICADO'!$C$21 -> 253.56175
A25: bolita de carne | N25: 55
A26: carne guisada | N26: ='[2]CARNE GUISADA'!$C$21 -> 155.53526
A27: mondongo | N27: =[2]MONDONGO!$C$21 -> 47.804304
A28: rabito
A29: costilla desayuno | N29: ='[3]COSTILLA FRITA'!$C$21 -> 226.64542
A30: bistec cinta | N30: 55
A31: higado | N31: =[3]HIGADO!$C$21 -> 78.967625
A32: carnes imprevistas | N32: 200
A33: bofe | N33: =[3]BOFE!$C$21 -> 193.70203
A35: 5009 - MARISCOS | B35: 243.92 | C35: 35 | D35: 660.61 | E35: 718.71 | F35: 327.19 | G35: 229.55 | H35: 407.15 | I35: 404.81 | J35: 571.52 | K35: 255.26236 | L35: 217.47 | M35: 233.47 | O35: =SUM(N36:N38)+150 -> 635.81056 | P35: 210.16
A36: filete de pescado | N36: ='[2]FILETE DE PESCADO'!$C$21 -> 283.16468
A37: corvina | N37: =[2]CORVINA!$C$22 -> 75.132288
A38: bacalao | N38: =[2]BACALAO!$C$21 -> 127.51358
A40: 5010 - POLLO | B40: 2737.95 | C40: 4080.58 | D40: 4712.83 | E40: 4507.88 | F40: 3669.39 | G40: 3739.36 | H40: 3624.15 | I40: 4356.64 | J40: 4446.79 | K40: 467.17438 | L40: 5278.2 | M40: 5977.99 | O40: =SUM(N41:N43) -> 4323.9313 | P40: 4058.86
A41: pollo | N41: ='[1]POLLO calculo'!$B$18 -> 4131.6058
A42: filete de pechuga parrilla | N42: ='[1]FILETE DE PECHUGA'!$C$22 -> 90.540205
A43: filete de pechuga criolla | N43: ='[2]FILETE PECHUGA '!$C$22 -> 101.78529
A45: 5011 - VIVERES (MENESTRAS, KETCHUP, OTROS) | B45: 3579.56 | C45: 3070.83 | D45: 3453.6 | E45: 1513.71 | F45: 1820.39 | G45: 1993.32 | H45: 3016.66 | I45: 2132.07 | J45: 2803.97 | K45: 4239.0395 | L45: 2920.89 | M45: 3103.51 | O45: =SUM(N46:N56) -> 1564.0177 | P45: 2462.5625
A46: porotos | N46: =[4]ARROZ!$E$21 -> 287.5
A47: lentejas | N47: =[4]ARROZ!$D$21 -> 222.75
A48: chorizo de parrilla | N48: ='[1]chorizo parrilla '!$C$21 -> 134.16826
A49: chorizo tableño
A50: almojabano | N50: =[3]ALMOJABANO!$C$20 -> 5.955
A51: salchicha para guisar | N51: ='[3]SALCHICHA GUI'!$C$22 -> 51.02482
A52: bollo | N52: =[3]BOLLO!$C$20 -> 157.642
A53: carimañola | N53: =[3]CARIMAÑOLA!$C$20 -> 60.78256
A54: tortilla | N54: =[3]TORTILLA!$C$20 -> 52.40274
A55: empa | N55: ='[3]EMP DE MAIZ'!$C$20 -> 41.792314
A56: otros viveres | N56: 550
A58: 5012 - SODAS, REFRESCOS AGUA | B58: 722.68 | C58: 1144.8 | D58: 1890.29 | E58: 1678 | F58: 1942.11 | G58: 1579.19 | H58: 962.47 | I58: 2453.66 | J58: 1489.57 | K58: 3194.5462 | L58: 2667.67 | M58: 2935.09 | O58: =N59+N60 -> 2526.2253 | P58: 2337.2067
A59: sodas | N59: =[1]SODAS!$B$21 -> 1826.2253
A60: otros | N60: 700
A62: 5013 - FIAMBRERAS, ENVASES VARIOS | B62: 1245.95 | C62: 1772.34 | D62: 1862.83 | E62: 1716.57 | F62: 2333.24 | G62: 1758.47 | H62: 1946.78 | I62: 1940.83 | J62: 2172.69 | K62: 606.87528 | L62: 551.74 | M62: 1401.58 | O62: 950 | P62: 1279.3088
A63: 5014 - ARROZ,LEGUMBRES,PAPITAS, ETC | B63: 396.48 | D63: 355.66 | E63: 406.74 | F63: 445.62 | G63: 437.82 | H63: 390.92 | I63: 745.22 | J63: 1216.11 | K63: 3397.5336 | L63: 2640.17 | M63: 3836.56 | O63: =SUM(N64:N69) -> 3546.8976 | P63: 3291.4212
A64: arroz | N64: =[1]ARROZ!$B$21 -> 922.40604
A65: perejil | N65: =[1]CHIMICHURRI!$B$20 -> 335.81108
A66: platano | N66: =[1]PATACONES!$B$21 -> 286.3487
A67: yuca | N67: =[1]yuca!$C$21 -> 296.38669
A68: papitas | N68: =[1]papitas!$C$24 -> 1205.945
A69: otras legumbres | N69: 500
A71: 6101 - GAS | B71: 2608.57 | C71: 2325.4 | D71: 2654.75 | E71: 2393.35 | F71: 2561.25 | G71: 2894.79 | H71: 2362.55 | I71: 2537.06 | J71: 2116.49 | K71: 2146.93 | L71: 2167.68 | M71: 2382.53 | O71: 2150 | P71: 2143.7 | Q71: ACTUAL
A72: Total Costo de Venta | B72: =SUM(B14:B71) -> 13684.66 | C72: =SUM(C14:C71) -> 14341.92 | D72: =SUM(D14:D71) -> 18353.91 | E72: =SUM(E14:E71) -> 15358.19 | F72: =SUM(F14:F71) -> 16075.15 | G72: =SUM(G14:G71) -> 15531.4 | H72: =SUM(H14:H71) -> 15709.02 | I72: =SUM(I14:I71) -> 18314.45 | ... M72: =SUM(M14:M71) -> 24249.73 | O72: =SUM(O14:O71) -> 20262.062 | P72: 19325.001 | Q72: 19867.9
A73: Beneficio Bruto | B73: =+B11-B72 -> 12034.52 | C73: =+C11-C72 -> 14903.44 | D73: =+D11-D72 -> 18842.42 | E73: =+E11-E72 -> 17295.01 | F73: =+F11-F72 -> 15810.68 | G73: =+G11-G72 -> 15880.32 | H73: =+H11-H72 -> 15578.51 | I73: =+I11-I72 -> 18140.66 | ... M73: =+M11-M72 -> 31884.22 | O73: =+O11-O72 -> 25937.804 | P73: 37720.678 | Q73: =Q11-Q72 -> -13089.634
A75: Gastos
P76: 99.291
A77: Gastos Operativos | O77: 0 | P77: 1742.5
A78: Salarios | O78: 5600 | P78: 148.83167
A79: Vacaciones | O79: 0 | P79: 760
A80: XIII Mes | O80: 0 | P80: 315.65667
A81: Prima de Antiguedad | O81: 0 | P81: 1815
A82: Indemnización | O82: 0 | P82: 38.41
A83: Preaviso | O83: 0 | P83: 1573.1725
A84: Cuota Patronal CSS | O84: 943.6 | P84: 220.58818
A85: Alquiler Local | O85: 2800
A86: Electricidad | O86: 1700 | P86: 118.07333
A87: Telefonía e Internet | O87: 112 | P87: 673.27417
A88: Agua y Aseo | O88: 19.76 | P88: 0
A89: Cargos Bancarios | O89: 150
A90: Cargos de Tarjetas de Crédito | O90: 200 | P90: 436.66125
A91: Seguros | O91: 617.18 | P91: 97.546667
A92: Honorarios Profesionales | O92: 1500 | P92: 132.60333
A93: Atención al Cliente | O93: 453.66 | P93: 488.8475
A94: VARIOS | O94: 50 | P94: 145.532
A95: Atención Empleado | O95: 453.66 | P95: 203.75
A96: Fletes y Acarreos | O96: 60 | P96: 4338.4583
A97: Gasolina y Lubricante | O97: 300
A98: Legales y Notariales | O98: 0
A99: Herramientas Pequeñas | O99: 0
A100: Impresos, Materiales e insumos | O100: 0
A101: Reparacion y Mant. Freidora In | O101: 100
A102: Reparación Equi de Informática | O102: 0
A103: Reparación y Mant. Eq de Ofici | O103: 0
A104: Reparación y Mant. Eq de Segur | O104: 0
A105: Reparación y Mant. Eq de Rodan | O105: 153.43
A106: Rep. y Mant. de Ofic/Local | O106: 25
A107: Gastos Médicos | O107: 175.88
A108: Papelería y Fotocopia | O108: 0
... A121: Multas y Recargos sobre Impues | O121: 0
A124: Total de Gastos operativos | B124: Total de Gastos operativos | C124: Total de Gastos operativos | D124: Total de Gastos operativos | E124: Total de Gastos operativos | F124: Total de Gastos operativos | G124: Total de Gastos operativos | H124: Total de Gastos operativos | I124: Total de Gastos operativos | J124: Total de Gastos operativos | K124: Total de Gastos operativos | L124: Total de Gastos operativos | M124: Total de Gastos operativos | O124: =SUM(O76:O123) -> 17210.94 | P124: 727.95333
O125: =O124/O9 -> 0.3442188 | P125: 26.075 | Q125: ACTUAL
...

Sheet Hoja1
C2: ='resultado estimado'!O72 -> 20262.062
B3: Presupuesto según porcentajes ideales | C3: =C2 -> 20262.062
B4: 5008 - CARNES Y PUERCO | C4: =$C$3*D4 -> 3820.2413 | D4: 0.18854158
B5: 5009 - MARISCOS | C5: =$C$3*D5 -> 343.42119 | D5: 0.016948975
B6: 5010 - POLLO | C6: =$C$3*D6 -> 4315.622 | D6: 0.21299027
B7: 5011 - VIVERES (MENESTRAS, KETCHUP, OTROS) | C7: =$C$3*D7 -> 2238.3315 | D7: 0.11046909
B8: 5012 - SODAS, REFRESCOS AGUA | C8: =$C$3*D8 -> 2447.7389 | D8: 0.12080404
B9: 5013 - FIAMBRERAS, ENVASES VARIOS | C9: =$C$3*D9 -> 1236.6238 | D9: 0.061031491
B10: 5014 - ARROZ,LEGUMBRES,PAPITAS, ETC | C10: =$C$3*D10 -> 3283.7836 | D10: 0.16206562
B11: 6101 - GAS | C11: =$C$3*D11 -> 2576.2997 | D11: 0.12714894

Sheet ventas
A1: fecha | B1: ventas efect | C1: ventas yappy | D1: ventas tarjetas | E1: ventas pedidos ya + uber | F1: total
A2: 45597 | B2: 1175.32 | C2: 127.62 | D2: =538.28+144.29+421.24 -> 1103.81 | F2: =SUM(B2:E29) -> 10161.8 | G2: 10578.4
A3: 45598 | B3: 913.26 | C3: 163.22 | D3: =326.25+156.5+464.02 -> 946.77 | G3: =F2-G2 -> -416.6
A4: 45599 | B4: 291.9 | C4: 36.6 | D4: =163.68+47.96+161.6 -> 373.24
A5: 45600 | B5: 403.78 | C5: 24.55 | D5: =217.04+65.99+228.39 -> 511.42
A6: 45601 | B6: 708.28 | C6: 98.32 | D6: =275.4+83.12+259.27 -> 617.79
A7: 45602 | B7: 678.07 | C7: 52.46 | D7: =164.13+16.84+127.72 -> 308.69
A8: 45603 | B8: 882.53 | C8: 78.75 | D8: =335.17+79.76+250.49 -> 665.42
A9: 45604
A10: 45605
A11: 45606
A12: 45607
A13: 45608
A14: 45609
A15: 45610
A16: 45611
A17: 45612
A18: 45613

Sheet ventas real
A1: fecha | B1: ventas efect | C1: ventas yappy | D1: ventas tarjetas | E1: ventas pedidos ya + uber | F1: total
A2: 45597 | B2: 1150.32 | F2: =SUM(B2:E29) -> 9935.53 | G2: =ventas!F2 -> 10161.8
A3: 45598 | B3: 913.26 | G3: =F2-G2 -> -226.27
A4: 45599 | B4: 291.9 | G4: =G3+ventas!G3 -> -642.87
A5: 45600 | B5: 403.78
A6: 45601 | B6: 688.28
A7: 45602 | B7: 648.07
A8: 45603 | B8: 882.53 | C8: 534.78 | D8: 4422.61
A9: 45604
A10: 45605
A11: 45606 | H11: =78.75+52.46+98.32+24.55+36.6+163.22+127.62 -> 581.52
A12: 45607
A13: 45608
A14: 45609
A15: 45610
A16: 45611
A17: 45612
A18: 45613
